mipsmulti.v
//-------------------------------------------------------
// mipsmulti.sv
// From David_Harris and Sarah_Harris book design
// Multicycle MIPS processor
//------------------------------------------------

module mips(input         clk, reset,
            output [31:0] adr, writedata,
            output        memwrite,
            input  [31:0] readdata);

  wire        zero, pcen, irwrite, regwrite,
               alusrca, iord, memtoreg, regdst;
              wire [3:0] alucontrol;
              wire [1:0] alusrcb, pcsrc;
              wire [5:0] op, funct;
 
  

  controller c(clk, reset, op, funct, zero,
               pcen, memwrite, irwrite, regwrite,
               alusrca, iord, memtoreg, regdst, 
               alusrcb, pcsrc, alucontrol); 
/*  datapath dp(clk, reset, 
              pcen, irwrite, regwrite,
              alusrca, iord, memtoreg, regdst,
              alusrcb, pcsrc, alucontrol,  
              op, funct, zero,
              adr, writedata, readdata);
*/
endmodule

module controller(input        clk, reset,
                  input  [5:0] op, funct,
                  input        zero,
                  output       pcen, memwrite, irwrite, regwrite,
                  output       alusrca, iord, memtoreg, regdst,
                  
                  output [1:0] alusrcb, pcsrc, 
		              output [3:0] alucontrol);
 		
  wire [1:0] aluop; 
  wire       branch, pcwrite;
  
  // Main Decoder and ALU Decoder subunits.
  maindec md(clk, reset, op,
             pcwrite, memwrite, irwrite, regwrite,
             alusrca, branch, iord, memtoreg, regdst, 
             alusrcb, pcsrc, aluop); 
  aludec  ad(funct, aluop, alucontrol);

  // ADD CODE HERE
  // Add combinational logic (i.e. an assign statement) 
  // to produce the PCEn signal (pcen) from the branch, 
  // zero, and pcwrite signals
  assign pcen = pcwrite | (branch & zero); 
 
 
 
endmodule

module maindec(input        clk, reset, 
               input  [5:0] op, 
               output       pcwrite, memwrite, irwrite, regwrite,
               output       alusrca, branch, iord, memtoreg, regdst,
               output [1:0] alusrcb, pcsrc, 
               output [1:0] aluop);
               

  parameter   FETCH   = 4'b0000; 	// State 0
  parameter   DECODE  = 4'b0001; 	// State 1
  parameter   MEMADR  = 4'b0010;	// State 2
  parameter   MEMRD   = 4'b0011;	// State 3
  parameter   MEMWB   = 4'b0100;	// State 4
  parameter   MEMWR   = 4'b0101;	// State 5
  parameter   RTYPEEX = 4'b0110;	// State 6
  parameter   RTYPEWB = 4'b0111;	// State 7
  parameter   BEQEX   = 4'b1000;	// State 8
  parameter   ADDIEX  = 4'b1001;	// State 9
  parameter   ADDIWB  = 4'b1010;	// state 10
  parameter   JEX     = 4'b1011;	// State 11

  parameter   LW      = 6'b100011;	// Opcode for lw
  parameter   SW      = 6'b101011;	// Opcode for sw
  parameter   RTYPE   = 6'b000000;	// Opcode for R-type
  parameter   BEQ     = 6'b000100;	// Opcode for beq
  parameter   ADDI    = 6'b001000;	// Opcode for addi
  parameter   J       = 6'b000010;	// Opcode for j


  reg [3:0]  state, nextstate;
  reg [14:0] controls;

  // state register
  always @(posedge clk or posedge reset)			
    if(reset) state <= FETCH;
    else state <= nextstate;

  // ADD CODE HERE
  // Finish entering the next state logic below.  We've completed the first 
  // two states, FETCH and DECODE, for you.

  // next state logic

  always @(*)
    case(state)
      FETCH:   nextstate <= DECODE;
      DECODE:  case(op)
                 LW:      nextstate <= MEMADR;
                 SW:      nextstate <= MEMADR;
                 RTYPE:   nextstate <= RTYPEEX;
                 BEQ:     nextstate <= BEQEX;
                 ADDI:    nextstate <= ADDIEX;
                 J:       nextstate <= JEX;
                 default: nextstate <= FETCH; // should never happen
                endcase
 		// Add code here
      MEMADR: case (op)
      		       LW:	    nextstate <= MEMRD;
                 SW:	    nextstate <= MEMWR;
                 default: nextstate <= FETCH;
                  // should never happen
                endcase
      		
      MEMRD:      nextstate <= MEMWB;
      MEMWB:      nextstate <= FETCH;
      MEMWR:      nextstate <= FETCH;
      RTYPEEX:    nextstate <= RTYPEWB;
      RTYPEWB:    nextstate <= FETCH;
      BEQEX:      nextstate <= FETCH;
      ADDIEX:     nextstate <= ADDIWB;
      ADDIWB:     nextstate <= FETCH;
      JEX:        nextstate <= FETCH;
      default: nextstate <= FETCH; // should never happen
    endcase

  // output logic
  assign {pcwrite, memwrite, irwrite, regwrite, 
          alusrca, branch, iord, memtoreg, regdst,
          alusrcb, pcsrc, aluop} = controls;

  // ADD CODE HERE
  // Finish entering the output logic below.  We've entered the
  // output logic for the first two states, S0 and S1, for you.
  always @(*)
    case(state)
      FETCH:   controls <= 15'h5010;
      DECODE:  controls <= 15'h0030;
    // your code goes here
      MEMADR  :  controls <= 15'h0420;
      MEMRD   :  controls <= 15'h0100;
      MEMWB   :  controls <= 15'h0880;
      MEMWR   :  controls <= 15'h2100;
      RTYPEEX :  controls <= 15'h0402;
      RTYPEWB :  controls <= 15'h0840;
      BEQEX   :  controls <= 15'h0605;
      ADDIEX  :  controls <= 15'h0420;
      ADDIWB  :  controls <= 15'h0800;
      JEX     :  controls <= 15'h4008;
      default: controls <= 15'hxxxx; // should never happen
    endcase
endmodule

module aludec(input  [5:0] funct,
              input  [1:0] aluop,
              output reg [3:0] alucontrol);

  // ADD CODE HERE
  // Complete the design for the ALU Decoder.
  // Your design goes here.  Remember that this is a combinational 
  // module. 

  // Remember that you may also reuse any code from previous labs.

   always@ (*)
    case(aluop)
      2'b00: alucontrol <= 4'b0000;  // add
      2'b01: alucontrol <= 4'b0010;  // sub
      2'b11: alucontrol <= 4'b0101;  // or                                            //NUEVA LINEAAAAAAAAAAAAAAAAAAAAAAAAAAAAAAAAAAAAAA
      default: case(funct)          // RTYPE
          6'b100000: alucontrol <= 4'b0000; // ADD
          6'b100010: alucontrol <= 4'b0010; // SUB
          6'b100100: alucontrol <= 4'b0100; // AND
          6'b100101: alucontrol <= 4'b0101; // OR
          6'b101010: alucontrol <= 4'b1010; // SLT
          default:   alucontrol <= 4'bxxx; // ???
        endcase
    endcase
endmodule



/*
// Complete the datapath module below for Lab 11.
// You do not need to complete this module for Lab 10

// The datapath unit is a structural verilog module.  That is,
// it is composed of instances of its sub-modules.  For example,
// the instruction register is instantiated as a 32-bit flopenr.
// The other submodules are likewise instantiated.

module datapath(input         clk, reset,
                input         pcen, irwrite, regwrite,
                input         alusrca, iord, memtoreg, regdst,
                input  [1:0]  alusrcb, pcsrc, 
                input  [2:0]  alucontrol,
                output [5:0]  op, funct,
                output        zero,
                output [31:0] adr, writedata, 
                input  [31:0] readdata);

  // Below are the internal signals of the datapath module.

  reg [4:0]  writereg;
  reg [31:0] pcnext, pc;
  reg [31:0] instr, data, srca, srcb;
  reg [31:0] a;
  reg [31:0] aluresult, aluout;
  reg [31:0] signimm;   // the sign-extended immediate
  reg [31:0] signimmsh;	// the sign-extended immediate shifted left by 2
  reg [31:0] wd3, rd1, rd2;

  // op and funct fields to controller
  assign op = instr[31:26];
  assign funct = instr[5:0];

  // Your datapath hardware goes below.  Instantiate each of the submodules
  // that you need.  Remember that alu's, mux's and various other 
  // versions of parameterizable modules are available in mipsparts.sv
  // from Lab 9. You'll likely want to include this verilog file in your
  // simulation.

  // We've included parameterizable 3:1 and 4:1 muxes below for your use.

  // Remember to give your instantiated modules applicable names
  // such as pcreg (PC register), wdmux (Write Data Mux), etc.
  // so it's easier to understand.

  // ADD CODE HERE

  // datapath
 
endmodule


module mux3 #(parameter WIDTH = 8)
             (input  [WIDTH-1:0] d0, d1, d2,
              input  [1:0]       s, 
              output [WIDTH-1:0] y);

  assign #1 y = s[1] ? d2 : (s[0] ? d1 : d0); 
endmodule

module mux4 #(parameter WIDTH = 8)
             (input  [WIDTH-1:0] d0, d1, d2, d3,
              input  [1:0]       s, 
              output [WIDTH-1:0] y);

   always_comb
      case(s)
         2'b00: y <= d0;
         2'b01: y <= d1;
         2'b10: y <= d2;
         2'b11: y <= d3;
      endcase
endmodule

*/

controllertest_tb.v
`include "mipsmulti.v"
module controllertest_tb;
        reg        clk, reset;
        reg  [5:0] op, funct;
        reg        zero;
        wire       pcen, memwrite, irwrite, regwrite;
        wire       alusrca, iord, memtoreg, regdst;
        wire [1:0] alusrcb, pcsrc;
        wire [3:0] alucontrol;

    initial
    begin
        clk = 1'b1;
        forever
            #5 clk = ~clk;
    end

    initial
    begin
        #0 reset = 1'b1; #1 reset = 1'b0;
        //------------------------------------------------- 
        op = 6'b100011; funct = 6'bxxxxxx; zero = 1'bx; #50 //LW: fetch decode memadr memrd memwb
        op = 6'b101011; funct = 6'bxxxxxx; zero = 1'bx; #40 //SW: memwr
        op = 6'b000000; funct = 6'b100000; zero = 1'bx; #40 //R-type: rtypeEx rtypewb
        op = 6'b000100; funct = 6'bxxxxxx; zero = 1'b1; #30 //BEQ: beqex
        op = 6'b001000; funct = 6'bxxxxxx; zero = 1'bx; #40 //ADDI: addiex addiwb
        op = 6'b000010; funct = 6'bxxxxxx; zero = 1'bx; #30 //J: jex
        
        $finish;
    end
    controller c(clk, reset, op, funct, zero,
               pcen, memwrite, irwrite, regwrite,
               alusrca, iord, memtoreg, regdst, 
               alusrcb, pcsrc, alucontrol);

    initial begin
        $dumpfile ("controllertest.vcd");
        $dumpvars;
    end
endmodule

controllertest.vcd
$date
	Fri Jul 17 17:00:35 2020
$end
$version
	Icarus Verilog
$end
$timescale
	1s
$end
$scope module controllertest_tb $end
$var wire 1 ! regwrite $end
$var wire 1 " regdst $end
$var wire 2 # pcsrc [1:0] $end
$var wire 1 $ pcen $end
$var wire 1 % memwrite $end
$var wire 1 & memtoreg $end
$var wire 1 ' irwrite $end
$var wire 1 ( iord $end
$var wire 2 ) alusrcb [1:0] $end
$var wire 1 * alusrca $end
$var wire 4 + alucontrol [3:0] $end
$var reg 1 , clk $end
$var reg 6 - funct [5:0] $end
$var reg 6 . op [5:0] $end
$var reg 1 / reset $end
$var reg 1 0 zero $end
$scope module c $end
$var wire 1 , clk $end
$var wire 6 1 funct [5:0] $end
$var wire 6 2 op [5:0] $end
$var wire 1 $ pcen $end
$var wire 1 / reset $end
$var wire 1 0 zero $end
$var wire 1 ! regwrite $end
$var wire 1 " regdst $end
$var wire 1 3 pcwrite $end
$var wire 2 4 pcsrc [1:0] $end
$var wire 1 % memwrite $end
$var wire 1 & memtoreg $end
$var wire 1 ' irwrite $end
$var wire 1 ( iord $end
$var wire 1 5 branch $end
$var wire 2 6 alusrcb [1:0] $end
$var wire 1 * alusrca $end
$var wire 2 7 aluop [1:0] $end
$var wire 4 8 alucontrol [3:0] $end
$scope module ad $end
$var wire 6 9 funct [5:0] $end
$var wire 2 : aluop [1:0] $end
$var reg 4 ; alucontrol [3:0] $end
$upscope $end
$scope module md $end
$var wire 1 , clk $end
$var wire 6 < op [5:0] $end
$var wire 1 / reset $end
$var wire 1 ! regwrite $end
$var wire 1 " regdst $end
$var wire 1 3 pcwrite $end
$var wire 2 = pcsrc [1:0] $end
$var wire 1 % memwrite $end
$var wire 1 & memtoreg $end
$var wire 1 ' irwrite $end
$var wire 1 ( iord $end
$var wire 1 5 branch $end
$var wire 2 > alusrcb [1:0] $end
$var wire 1 * alusrca $end
$var wire 2 ? aluop [1:0] $end
$var reg 15 @ controls [14:0] $end
$var reg 4 A nextstate [3:0] $end
$var reg 4 B state [3:0] $end
$upscope $end
$upscope $end
$upscope $end
$scope module mips $end
$var wire 32 C adr [31:0] $end
$var wire 1 D clk $end
$var wire 6 E funct [5:0] $end
$var wire 6 F op [5:0] $end
$var wire 32 G readdata [31:0] $end
$var wire 1 H reset $end
$var wire 32 I writedata [31:0] $end
$var wire 1 J zero $end
$var wire 1 K regwrite $end
$var wire 1 L regdst $end
$var wire 2 M pcsrc [1:0] $end
$var wire 1 N pcen $end
$var wire 1 O memwrite $end
$var wire 1 P memtoreg $end
$var wire 1 Q irwrite $end
$var wire 1 R iord $end
$var wire 2 S alusrcb [1:0] $end
$var wire 1 T alusrca $end
$var wire 4 U alucontrol [3:0] $end
$scope module c $end
$var wire 1 D clk $end
$var wire 6 V funct [5:0] $end
$var wire 6 W op [5:0] $end
$var wire 1 N pcen $end
$var wire 1 H reset $end
$var wire 1 J zero $end
$var wire 1 K regwrite $end
$var wire 1 L regdst $end
$var wire 1 X pcwrite $end
$var wire 2 Y pcsrc [1:0] $end
$var wire 1 O memwrite $end
$var wire 1 P memtoreg $end
$var wire 1 Q irwrite $end
$var wire 1 R iord $end
$var wire 1 Z branch $end
$var wire 2 [ alusrcb [1:0] $end
$var wire 1 T alusrca $end
$var wire 2 \ aluop [1:0] $end
$var wire 4 ] alucontrol [3:0] $end
$scope module ad $end
$var wire 6 ^ funct [5:0] $end
$var wire 2 _ aluop [1:0] $end
$var reg 4 ` alucontrol [3:0] $end
$upscope $end
$scope module md $end
$var wire 1 D clk $end
$var wire 6 a op [5:0] $end
$var wire 1 H reset $end
$var wire 1 K regwrite $end
$var wire 1 L regdst $end
$var wire 1 X pcwrite $end
$var wire 2 b pcsrc [1:0] $end
$var wire 1 O memwrite $end
$var wire 1 P memtoreg $end
$var wire 1 Q irwrite $end
$var wire 1 R iord $end
$var wire 1 Z branch $end
$var wire 2 c alusrcb [1:0] $end
$var wire 1 T alusrca $end
$var wire 2 d aluop [1:0] $end
$var reg 15 e controls [14:0] $end
$var reg 4 f nextstate [3:0] $end
$var reg 4 g state [3:0] $end
$upscope $end
$upscope $end
$upscope $end
$enddefinitions $end
#0
$dumpvars
bx g
b0 f
bx e
bx d
bx c
bx b
bz a
bx `
bx _
bz ^
bx ]
bx \
bx [
xZ
bx Y
xX
bz W
bz V
bx U
xT
bx S
xR
xQ
xP
xO
xN
bx M
xL
xK
zJ
bz I
zH
bz G
bz F
bz E
zD
bz C
b0 B
b1 A
b101000000010000 @
b0 ?
b1 >
b0 =
bx <
b0 ;
b0 :
bx 9
b0 8
b0 7
b1 6
05
b0 4
13
bx 2
bx 1
x0
1/
bx .
bx -
1,
b0 +
0*
b1 )
0(
1'
0&
0%
1$
b0 #
0"
0!
$end
#1
b100011 .
b100011 2
b100011 <
0/
#5
0,
#10
0$
03
0'
b11 )
b11 6
b11 >
b110000 @
b10 A
b1 B
1,
#15
0,
#20
1*
b10 )
b10 6
b10 >
b10000100000 @
b11 A
b10 B
1,
#25
0,
#30
0*
1(
b0 )
b0 6
b0 >
b100000000 @
b100 A
b11 B
1,
#35
0,
#40
1!
0(
1&
b100010000000 @
b0 A
b100 B
1,
#45
0,
#50
1$
13
1'
0!
0&
b1 )
b1 6
b1 >
b101000000010000 @
b1 A
b0 B
1,
#51
b101011 .
b101011 2
b101011 <
#55
0,
#60
0$
03
0'
b11 )
b11 6
b11 >
b110000 @
b10 A
b1 B
1,
#65
0,
#70
1*
b10 )
b10 6
b10 >
b10000100000 @
b101 A
b10 B
1,
#75
0,
#80
1%
0*
1(
b0 )
b0 6
b0 >
b10000100000000 @
b0 A
b101 B
1,
#85
0,
#90
1$
13
0%
1'
0(
b1 )
b1 6
b1 >
b101000000010000 @
b1 A
b0 B
1,
#91
b100000 -
b100000 1
b100000 9
b0 .
b0 2
b0 <
#95
0,
#100
0$
03
0'
b11 )
b11 6
b11 >
b110000 @
b110 A
b1 B
1,
#105
0,
#110
1*
b0 )
b0 6
b0 >
b10 7
b10 :
b10 ?
b10000000010 @
b111 A
b110 B
1,
#115
0,
#120
1!
0*
1"
b0 7
b0 :
b0 ?
b100001000000 @
b0 A
b111 B
1,
#125
0,
#130
1$
13
1'
0!
0"
b1 )
b1 6
b1 >
b101000000010000 @
b1 A
b0 B
1,
#131
10
bx -
bx 1
bx 9
b100 .
b100 2
b100 <
#135
0,
#140
0$
03
0'
b11 )
b11 6
b11 >
b110000 @
b1000 A
b1 B
1,
#145
0,
#150
b10 +
b10 8
b10 ;
1$
1*
15
b0 )
b0 6
b0 >
b1 #
b1 4
b1 =
b1 7
b1 :
b1 ?
b11000000101 @
b0 A
b1000 B
1,
#155
0,
#160
b0 +
b0 8
b0 ;
13
1'
0*
05
b1 )
b1 6
b1 >
b0 #
b0 4
b0 =
b0 7
b0 :
b0 ?
b101000000010000 @
b1 A
b0 B
1,
#161
x0
b1000 .
b1000 2
b1000 <
#165
0,
#170
0$
03
0'
b11 )
b11 6
b11 >
b110000 @
b1001 A
b1 B
1,
#175
0,
#180
1*
b10 )
b10 6
b10 >
b10000100000 @
b1010 A
b1001 B
1,
#185
0,
#190
1!
0*
b0 )
b0 6
b0 >
b100000000000 @
b0 A
b1010 B
1,
#195
0,
#200
1$
13
1'
0!
b1 )
b1 6
b1 >
b101000000010000 @
b1 A
b0 B
1,
#201
b10 .
b10 2
b10 <
#205
0,
#210
0$
03
0'
b11 )
b11 6
b11 >
b110000 @
b1011 A
b1 B
1,
#215
0,
#220
1$
13
b0 )
b0 6
b0 >
b10 #
b10 4
b10 =
b100000000001000 @
b0 A
b1011 B
1,
#225
0,
#230
1'
b1 )
b1 6
b1 >
b0 #
b0 4
b0 =
b101000000010000 @
b1 A
b0 B
1,
